{"WA": {"Autre": 347165.0, "color": "#3399FF", "Clinton": 1742718.0, "Trump": 1221747.0, "Blanc": 51770.0}, "DE": {"Autre": 20860.0, "color": "#3399FF", "Clinton": 265603.0, "Trump": 185127.0, "Blanc": 0.0}, "DC": {"Autre": 15715.0, "color": "#3399FF", "Clinton": 282830.0, "Trump": 12723.0, "Blanc": 61307.0}, "WI": {"Autre": 188330.0, "color": "#FF0000", "Clinton": 1382536.0, "Trump": 1405284.0, "Blanc": 0.0}, "WV": {"Autre": 34886.0, "color": "#FF0000", "Clinton": 188794.0, "Trump": 489371.0, "Blanc": 0.0}, "HI": {"Autre": 176699.0, "color": "#3399FF", "Clinton": 266891.0, "Trump": 128847.0, "Blanc": 8727.0}, "FL": {"Autre": 297178.0, "color": "#FF0000", "Clinton": 4504975.0, "Trump": 4617886.0, "Blanc": 0.0}, "WY": {"Autre": 25457.0, "color": "#FF0000", "Clinton": 55973.0, "Trump": 174419.0, "Blanc": 0.0}, "NH": {"Autre": 49865.0, "color": "#3399FF", "Clinton": 348526.0, "Trump": 345790.0, "Blanc": 0.0}, "NJ": {"Autre": 123835.0, "color": "#3399FF", "Clinton": 2148278.0, "Trump": 1601933.0, "Blanc": 83257.0}, "NM": {"Autre": 93418.0, "color": "#3399FF", "Clinton": 385234.0, "Trump": 319666.0, "Blanc": 5725.0}, "TX": {"Autre": 406311.0, "color": "#FF0000", "Clinton": 3877868.0, "Trump": 4685047.0, "Blanc": 865492.0}, "NC": {"Autre": 189617.0, "color": "#FF0000", "Clinton": 2189316.0, "Trump": 2362631.0, "Blanc": 28076.0}, "ND": {"Autre": 33808.0, "color": "#FF0000", "Clinton": 93758.0, "Trump": 216794.0, "Blanc": 0.0}, "NE": {"Autre": 63772.0, "color": "#FF0000", "Clinton": 284494.0, "Trump": 495961.0, "Blanc": 16346.0}, "TN": {"Autre": 114407.0, "color": "#FF0000", "Clinton": 870695.0, "Trump": 1522925.0, "Blanc": 0.0}, "NY": {"Autre": 348562.0, "color": "#3399FF", "Clinton": 4547418.0, "Trump": 2814346.0, "Blanc": 76738.0}, "PA": {"Autre": 218228.0, "color": "#FF0000", "Clinton": 2926441.0, "Trump": 2970733.0, "Blanc": 0.0}, "LS": {"Autre": 70240.0, "color": "#FF0000", "Clinton": 780154.0, "Trump": 1178638.0, "Blanc": 0.0}, "CA": {"Autre": 943986.0, "color": "#3399FF", "Clinton": 8753788.0, "Trump": 4483810.0, "Blanc": 428915.0}, "NV": {"Autre": 74067.0, "color": "#3399FF", "Clinton": 539260.0, "Trump": 512058.0, "Blanc": 0.0}, "VA": {"Autre": 231836.0, "color": "#3399FF", "Clinton": 1981473.0, "Trump": 1769443.0, "Blanc": 0.0}, "CO": {"Autre": 238866.0, "color": "#3399FF", "Clinton": 1338870.0, "Trump": 1202484.0, "Blanc": 78996.0}, "AK": {"Autre": 38767.0, "color": "#FF0000", "Clinton": 116454.0, "Trump": 163387.0, "Blanc": 2666.0}, "AL": {"Autre": 75570.0, "color": "#FF0000", "Clinton": 729547.0, "Trump": 1318255.0, "Blanc": 14110.0}, "AR": {"Autre": 65269.0, "color": "#FF0000", "Clinton": 380494.0, "Trump": 684872.0, "Blanc": 7137.0}, "VT": {"Autre": 41125.0, "color": "#3399FF", "Clinton": 178573.0, "Trump": 95369.0, "Blanc": 0.0}, "IL": {"Autre": 299680.0, "color": "#3399FF", "Clinton": 3090729.0, "Trump": 2146015.0, "Blanc": 0.0}, "GA": {"Autre": 125306.0, "color": "#FF0000", "Clinton": 1877963.0, "Trump": 2089104.0, "Blanc": 73032.0}, "IN": {"Autre": 144549.0, "color": "#FF0000", "Clinton": 1033126.0, "Trump": 1557286.0, "Blanc": 0.0}, "IA": {"Autre": 111380.0, "color": "#FF0000", "Clinton": 653669.0, "Trump": 800983.0, "Blanc": 0.0}, "OK": {"Autre": 83481.0, "color": "#FF0000", "Clinton": 420375.0, "Trump": 949136.0, "Blanc": 0.0}, "AZ": {"Autre": 159647.0, "color": "#FF0000", "Clinton": 1161167.0, "Trump": 1252401.0, "Blanc": 88332.0}, "ID": {"Autre": 91435.0, "color": "#FF0000", "Clinton": 189765.0, "Trump": 409055.0, "Blanc": 20622.0}, "CT": {"Autre": 74133.0, "color": "#3399FF", "Clinton": 897572.0, "Trump": 673215.0, "Blanc": 31014.0}, "ME": {"Autre": 54593.0, "color": "#3399FF", "Clinton": 357335.0, "Trump": 335593.0, "Blanc": 0.0}, "MD": {"Autre": 160349.0, "color": "#3399FF", "Clinton": 1677928.0, "Trump": 943169.0, "Blanc": 0.0}, "MA": {"Autre": 238957.0, "color": "#3399FF", "Clinton": 1995196.0, "Trump": 1090893.0, "Blanc": 0.0}, "OH": {"Autre": 301734.0, "color": "#FF0000", "Clinton": 2394164.0, "Trump": 2841005.0, "Blanc": 70738.0}, "UT": {"Autre": 305523.0, "color": "#FF0000", "Clinton": 310676.0, "Trump": 515231.0, "Blanc": 0.0}, "MO": {"Autre": 143023.0, "color": "#FF0000", "Clinton": 1071068.0, "Trump": 1594511.0, "Blanc": 0.0}, "MN": {"Autre": 254146.0, "color": "#3399FF", "Clinton": 1367716.0, "Trump": 1322951.0, "Blanc": 0.0}, "MI": {"Autre": 250863.0, "color": "#FF0000", "Clinton": 2268839.0, "Trump": 2279543.0, "Blanc": 0.0}, "RI": {"Autre": 31076.0, "color": "#3399FF", "Clinton": 252525.0, "Trump": 180543.0, "Blanc": 0.0}, "KS": {"Autre": 86378.0, "color": "#FF0000", "Clinton": 427005.0, "Trump": 671018.0, "Blanc": 0.0}, "MT": {"Autre": 40197.0, "color": "#FF0000", "Clinton": 177709.0, "Trump": 279240.0, "Blanc": 19755.0}, "MS": {"Autre": 25243.0, "color": "#FF0000", "Clinton": 485131.0, "Trump": 700714.0, "Blanc": 0.0}, "SC": {"Autre": 92265.0, "color": "#FF0000", "Clinton": 855373.0, "Trump": 1155389.0, "Blanc": 0.0}, "KY": {"Autre": 92324.0, "color": "#FF0000", "Clinton": 628854.0, "Trump": 1202971.0, "Blanc": 25105.0}, "OR": {"Autre": 216827.0, "color": "#3399FF", "Clinton": 1002106.0, "Trump": 782404.0, "Blanc": 0.0}, "SD": {"Autre": 24914.0, "color": "#FF0000", "Clinton": 117458.0, "Trump": 227721.0, "Blanc": 0.0}}